mcm_cli-1.8.1.dist-info/licenses/LICENSE
mcm_cli-1.8.1.dist-info/licenses/NOTICE
mcmcli/__init__.py
mcmcli/__main__.py
mcmcli/logging.py
mcmcli/requests.py
mcmcli/command/account.py
mcmcli/command/admin.py
mcmcli/command/auth.py
mcmcli/command/campaign.py
mcmcli/command/config.py
mcmcli/command/decision.py
mcmcli/command/report.py
mcmcli/command/userevent.py
mcmcli/command/wallet.py
mcmcli/data/account.py
mcmcli/data/account_user.py
mcmcli/data/campaign.py
mcmcli/data/decision.py
mcmcli/data/error.py
mcmcli/data/item.py
mcmcli/data/item_blocking_result.py
mcmcli/data/platform_user.py
mcmcli/data/report.py
mcmcli/data/seller.py
mcmcli/data/token.py
mcmcli/data/user_join_request.py
mcmcli/data/wallet.py
mcm_cli-1.8.1.dist-info/METADATA
mcm_cli-1.8.1.dist-info/WHEEL
mcm_cli-1.8.1.dist-info/entry_points.txt
mcm_cli-1.8.1.dist-info/top_level.txt
mcm_cli-1.8.1.dist-info/RECORD
