Metadata-Version: 2.4
Name: mcm_cli
Version: 1.8.1
Summary: A command-line interface for Moloco Commerde Media
Home-page: https://github.com/moloco-mcm/mcm-cli
Author: Moloco MCM Team
Author-email: mcm-help@moloco.com
License: Apache-2.0 license
Classifier: Programming Language :: Python :: 3
Classifier: License :: OSI Approved :: Apache Software License
Classifier: Operating System :: OS Independent
Requires-Python: >=3.6
License-File: LICENSE
License-File: NOTICE
Requires-Dist: colorama
Requires-Dist: gitpython
Requires-Dist: pydantic
Requires-Dist: pygithub
Requires-Dist: python-terraform
Requires-Dist: requests
Requires-Dist: rich
Requires-Dist: setuptools
Requires-Dist: shortuuid
Requires-Dist: toml
Requires-Dist: typer
Dynamic: author
Dynamic: author-email
Dynamic: classifier
Dynamic: description
Dynamic: description-content-type
Dynamic: home-page
Dynamic: license
Dynamic: license-file
Dynamic: requires-dist
Dynamic: requires-python
Dynamic: summary
